main.py
modal_cuda-0.1.2.dist-info/licenses/LICENSE
modal_cuda-0.1.2.dist-info/METADATA
modal_cuda-0.1.2.dist-info/WHEEL
modal_cuda-0.1.2.dist-info/entry_points.txt
modal_cuda-0.1.2.dist-info/top_level.txt
modal_cuda-0.1.2.dist-info/RECORD
