Metadata-Version: 2.4
Name: modal-cuda
Version: 0.1.2
Summary: CLI that compiles and runs CUDA C programs on Modal GPUs
Author: ExpressGradient
License: MIT License
Requires-Python: >=3.12
License-File: LICENSE
Requires-Dist: modal>=1.2.2
Dynamic: license-file
